{"kind":"Article","sha256":"6692ffc49d32bd53baf722e7c35d944712ad2041e619d9c5ae92f1b5aa75a2bb","slug":"rainymotion","location":"/projects/rainymotion.md","dependencies":[],"frontmatter":{"title":"rainymotion","authors":[{"id":"Georgy Ayzel, Maik Heistermann","name":"Georgy Ayzel, Maik Heistermann"}],"date":"2018-08-28","content_includes_title":false,"open_access":true,"license":{"content":{"id":"Apache-2.0","name":"Apache License 2.0","osi":true,"free":true,"url":"https://opensource.org/licenses/Apache-2.0"},"code":{"id":"CC-BY-4.0","name":"Creative Commons Attribution 4.0 International","free":true,"CC":true,"url":"https://creativecommons.org/licenses/by/4.0/"}},"github":"https://github.com/openradar","copyright":"2024","exports":[{"format":"md","filename":"rainymotion.md","url":"/openradar.github.io/_preview/3/build/rainymotion-c2816e7c4c2dd30b8b5e2a11bbe20278.md"}]},"mdast":{"type":"root","children":[{"type":"block","children":[{"type":"heading","depth":2,"position":{"start":{"line":9,"column":1},"end":{"line":9,"column":1}},"children":[{"type":"text","value":"Quick description","position":{"start":{"line":9,"column":1},"end":{"line":9,"column":1}},"key":"DydfRItUVz"}],"identifier":"quick-description","label":"Quick description","html_id":"quick-description","implicit":true,"key":"yd3QAGsaX2"},{"type":"paragraph","position":{"start":{"line":11,"column":1},"end":{"line":11,"column":1}},"children":[{"type":"inlineCode","value":"rainymotion","position":{"start":{"line":11,"column":1},"end":{"line":11,"column":1}},"key":"g2zpvFcdOu"},{"type":"text","value":" is a Python library for radar-based precipitation nowcasting based on optical flow techniques. The main idea is to provide a stack of open models which can serve as a transparent benchmark for further development of nowcasting techniques. An extensive verification study in Germany has shown that the ","position":{"start":{"line":11,"column":1},"end":{"line":11,"column":1}},"key":"bIWaXNzzbg"},{"type":"inlineCode","value":"rainymotion","position":{"start":{"line":11,"column":1},"end":{"line":11,"column":1}},"key":"Y1wWFygUCW"},{"type":"text","value":" models based on Dense optical flow are at least equivalent if not superior to state-of-the-art operational nowcasting techniques.","position":{"start":{"line":11,"column":1},"end":{"line":11,"column":1}},"key":"tdsxm5Eh50"}],"key":"xpwLaGCI9F"},{"type":"heading","depth":2,"position":{"start":{"line":13,"column":1},"end":{"line":13,"column":1}},"children":[{"type":"text","value":"Homepage","position":{"start":{"line":13,"column":1},"end":{"line":13,"column":1}},"key":"T4DmSe0DnO"}],"identifier":"homepage","label":"Homepage","html_id":"homepage","implicit":true,"key":"ND6mmjb7xn"},{"type":"paragraph","position":{"start":{"line":15,"column":1},"end":{"line":15,"column":1}},"children":[{"type":"link","url":"https://rainymotion.readthedocs.io","position":{"start":{"line":15,"column":1},"end":{"line":15,"column":1}},"children":[{"type":"text","value":"https://​rainymotion​.readthedocs​.io","position":{"start":{"line":15,"column":1},"end":{"line":15,"column":1}},"key":"cV0pVqK2jC"}],"urlSource":"https://rainymotion.readthedocs.io","key":"pG4KobrBHw"}],"key":"zZs7BGJTsX"},{"type":"heading","depth":2,"position":{"start":{"line":17,"column":1},"end":{"line":17,"column":1}},"children":[{"type":"text","value":"Code Repository","position":{"start":{"line":17,"column":1},"end":{"line":17,"column":1}},"key":"yzv7HFLo8N"}],"identifier":"code-repository","label":"Code Repository","html_id":"code-repository","implicit":true,"key":"eFBTidpNBw"},{"type":"paragraph","position":{"start":{"line":19,"column":1},"end":{"line":19,"column":1}},"children":[{"type":"link","url":"https://github.com/hydrogo/rainymotion","position":{"start":{"line":19,"column":1},"end":{"line":19,"column":1}},"children":[{"type":"text","value":"https://​github​.com​/hydrogo​/rainymotion","position":{"start":{"line":19,"column":1},"end":{"line":19,"column":1}},"key":"lGgzs37fdW"}],"urlSource":"https://github.com/hydrogo/rainymotion","error":true,"key":"B5ROdyZOct"}],"key":"LEyrmJIxca"},{"type":"heading","depth":2,"position":{"start":{"line":21,"column":1},"end":{"line":21,"column":1}},"children":[{"type":"text","value":"Software Documentation","position":{"start":{"line":21,"column":1},"end":{"line":21,"column":1}},"key":"eT06Bj8yHl"}],"identifier":"software-documentation","label":"Software Documentation","html_id":"software-documentation","implicit":true,"key":"sy5C4QWRzk"},{"type":"paragraph","position":{"start":{"line":23,"column":1},"end":{"line":23,"column":1}},"children":[{"type":"link","url":"https://rainymotion.readthedocs.io","position":{"start":{"line":23,"column":1},"end":{"line":23,"column":1}},"children":[{"type":"text","value":"https://​rainymotion​.readthedocs​.io","position":{"start":{"line":23,"column":1},"end":{"line":23,"column":1}},"key":"xxdOnYXErD"}],"urlSource":"https://rainymotion.readthedocs.io","key":"AM3aZFnSds"}],"key":"UEZs4scvR6"},{"type":"heading","depth":2,"position":{"start":{"line":25,"column":1},"end":{"line":25,"column":1}},"children":[{"type":"text","value":"License model","position":{"start":{"line":25,"column":1},"end":{"line":25,"column":1}},"key":"Lzc2F4xzQb"}],"identifier":"license-model","label":"License model","html_id":"license-model","implicit":true,"key":"MrFNiPMgI4"},{"type":"paragraph","position":{"start":{"line":26,"column":1},"end":{"line":26,"column":1}},"children":[{"type":"text","value":"MIT","position":{"start":{"line":26,"column":1},"end":{"line":26,"column":1}},"key":"EBw5dcNFKw"}],"key":"ddYXOb97FY"},{"type":"heading","depth":2,"position":{"start":{"line":28,"column":1},"end":{"line":28,"column":1}},"children":[{"type":"text","value":"Year of first release","position":{"start":{"line":28,"column":1},"end":{"line":28,"column":1}},"key":"NAvVhpuC4l"}],"identifier":"year-of-first-release","label":"Year of first release","html_id":"year-of-first-release","implicit":true,"key":"YOuRvyCVjL"},{"type":"paragraph","position":{"start":{"line":29,"column":1},"end":{"line":29,"column":1}},"children":[{"type":"text","value":"2018","position":{"start":{"line":29,"column":1},"end":{"line":29,"column":1}},"key":"Ej2AZaCZaM"}],"key":"oSGNJJySzn"},{"type":"heading","depth":2,"position":{"start":{"line":31,"column":1},"end":{"line":31,"column":1}},"children":[{"type":"text","value":"Main programming language","position":{"start":{"line":31,"column":1},"end":{"line":31,"column":1}},"key":"WhpQIDZSVW"}],"identifier":"main-programming-language","label":"Main programming language","html_id":"main-programming-language","implicit":true,"key":"zWwTncuk1Y"},{"type":"paragraph","position":{"start":{"line":32,"column":1},"end":{"line":32,"column":1}},"children":[{"type":"text","value":"Python","position":{"start":{"line":32,"column":1},"end":{"line":32,"column":1}},"key":"cFcGOodMXN"}],"key":"ZXcssK8NbQ"},{"type":"heading","depth":2,"position":{"start":{"line":34,"column":1},"end":{"line":34,"column":1}},"children":[{"type":"text","value":"Supported platforms","position":{"start":{"line":34,"column":1},"end":{"line":34,"column":1}},"key":"V0GFyqtQ10"}],"identifier":"supported-platforms","label":"Supported platforms","html_id":"supported-platforms","implicit":true,"key":"ZGB6EihjIF"},{"type":"paragraph","position":{"start":{"line":35,"column":1},"end":{"line":35,"column":1}},"children":[{"type":"text","value":"Linux, Mac, Windows","position":{"start":{"line":35,"column":1},"end":{"line":35,"column":1}},"key":"ML08IOBvl5"}],"key":"DHRlaTDA99"},{"type":"heading","depth":2,"position":{"start":{"line":37,"column":1},"end":{"line":37,"column":1}},"children":[{"type":"text","value":"Type of software","position":{"start":{"line":37,"column":1},"end":{"line":37,"column":1}},"key":"lPtmBNUcZG"}],"identifier":"type-of-software","label":"Type of software","html_id":"type-of-software","implicit":true,"key":"DKum3McYLN"},{"type":"paragraph","position":{"start":{"line":38,"column":1},"end":{"line":38,"column":1}},"children":[{"type":"text","value":"API/Library","position":{"start":{"line":38,"column":1},"end":{"line":38,"column":1}},"key":"QF0kvfzI6s"}],"key":"mRX1omwKVd"},{"type":"heading","depth":2,"position":{"start":{"line":40,"column":1},"end":{"line":40,"column":1}},"children":[{"type":"text","value":"References","position":{"start":{"line":40,"column":1},"end":{"line":40,"column":1}},"key":"ZUbgOm9vBK"}],"identifier":"references","label":"References","html_id":"references","implicit":true,"key":"wpZ3jYcUHz"},{"type":"paragraph","position":{"start":{"line":41,"column":1},"end":{"line":41,"column":1}},"children":[{"type":"text","value":"Ayzel, G., Heistermann, M., Winterrath, T. (2018): Optical flow models as an open benchmark for radar-based precipitation nowcasting (rainymotion v0.1), manuscript submitted to Geoscientific Model Development.","position":{"start":{"line":41,"column":1},"end":{"line":41,"column":1}},"key":"vjS41d3lDD"}],"key":"DgPguSf7L2"}],"key":"Qe3cHuww6e"}],"key":"Vpbri9Sn7b"},"references":{"cite":{"order":[],"data":{}}},"footer":{"navigation":{"prev":{"title":"Radx","url":"/radx","group":"OpenRadarScience"},"next":{"title":"RSL in IDL","url":"/rsl-in-idl","group":"OpenRadarScience"}}},"domain":"http://localhost:3000"}