{"kind":"Article","sha256":"5885ae38a4d5d811b0f3543d77c2eff3d7ccafd93cc8b6c0a2e61847b60aa3ba","slug":"rsl","location":"/projects/rsl.md","dependencies":[],"frontmatter":{"title":"RSL","authors":[{"id":"openradar","name":"openradar"}],"date":"2017-09-16","content_includes_title":false,"open_access":true,"license":{"content":{"id":"Apache-2.0","name":"Apache License 2.0","osi":true,"free":true,"url":"https://opensource.org/licenses/Apache-2.0"},"code":{"id":"CC-BY-4.0","name":"Creative Commons Attribution 4.0 International","free":true,"CC":true,"url":"https://creativecommons.org/licenses/by/4.0/"}},"github":"https://github.com/openradar","copyright":"2024","exports":[{"format":"md","filename":"rsl.md","url":"/kmuehlbauer.github.io/openradar.github.io/build/rsl-fe592e885b9b8c26eade4a2a285f1930.md"}]},"mdast":{"type":"root","children":[{"type":"block","children":[{"type":"heading","depth":2,"position":{"start":{"line":9,"column":1},"end":{"line":9,"column":1}},"children":[{"type":"text","value":"Quick description","position":{"start":{"line":9,"column":1},"end":{"line":9,"column":1}},"key":"XIVRL1GuXb"}],"identifier":"quick-description","label":"Quick description","html_id":"quick-description","implicit":true,"key":"cGJMegrwkb"},{"type":"paragraph","position":{"start":{"line":10,"column":1},"end":{"line":10,"column":1}},"children":[{"type":"text","value":"NASA’s Radar Software Library (RSL) was developed to support the Tropical Rainfall Measuring Mission (TRMM). It is designed to read data from a variety of weather radar formats into a uniform structure, and provide tools for working with the data. It is written in the C language.","position":{"start":{"line":10,"column":1},"end":{"line":10,"column":1}},"key":"SJRWP8j4Mh"}],"key":"hxrDiJIdPm"},{"type":"heading","depth":2,"position":{"start":{"line":12,"column":1},"end":{"line":12,"column":1}},"children":[{"type":"text","value":"Homepage","position":{"start":{"line":12,"column":1},"end":{"line":12,"column":1}},"key":"LgZ8msSNiQ"}],"identifier":"homepage","label":"Homepage","html_id":"homepage","implicit":true,"key":"HBdsolYgzI"},{"type":"paragraph","position":{"start":{"line":13,"column":1},"end":{"line":13,"column":1}},"children":[{"type":"link","url":"https://trmm-fc.gsfc.nasa.gov/trmm_gv/software/rsl/","position":{"start":{"line":13,"column":1},"end":{"line":13,"column":1}},"children":[{"type":"text","value":"https://​trmm​-fc​.gsfc​.nasa​.gov​/trmm​_gv​/software​/rsl​/","position":{"start":{"line":13,"column":1},"end":{"line":13,"column":1}},"key":"DyvlKpLiuN"}],"urlSource":"https://trmm-fc.gsfc.nasa.gov/trmm_gv/software/rsl/","key":"Re6KbcgwSd"}],"key":"RBSQo5F66w"},{"type":"heading","depth":2,"position":{"start":{"line":15,"column":1},"end":{"line":15,"column":1}},"children":[{"type":"text","value":"Code Repository","position":{"start":{"line":15,"column":1},"end":{"line":15,"column":1}},"key":"WlArKBSwXG"}],"identifier":"code-repository","label":"Code Repository","html_id":"code-repository","implicit":true,"key":"mCKo5wRCTO"},{"type":"paragraph","position":{"start":{"line":16,"column":1},"end":{"line":16,"column":1}},"children":[{"type":"text","value":"N/A","position":{"start":{"line":16,"column":1},"end":{"line":16,"column":1}},"key":"XUBF631dcU"}],"key":"Sv4XnsLld7"},{"type":"heading","depth":2,"position":{"start":{"line":18,"column":1},"end":{"line":18,"column":1}},"children":[{"type":"text","value":"Software Documentation","position":{"start":{"line":18,"column":1},"end":{"line":18,"column":1}},"key":"bamcuLubKV"}],"identifier":"software-documentation","label":"Software Documentation","html_id":"software-documentation","implicit":true,"key":"q8MJZbul3L"},{"type":"paragraph","position":{"start":{"line":19,"column":1},"end":{"line":19,"column":1}},"children":[{"type":"link","url":"https://trmm-fc.gsfc.nasa.gov/trmm_gv/software/rsl/quick_ref.php","position":{"start":{"line":19,"column":1},"end":{"line":19,"column":1}},"children":[{"type":"text","value":"https://​trmm​-fc​.gsfc​.nasa​.gov​/trmm​_gv​/software​/rsl​/quick​_ref​.php","position":{"start":{"line":19,"column":1},"end":{"line":19,"column":1}},"key":"TjDQaMhIF8"}],"urlSource":"https://trmm-fc.gsfc.nasa.gov/trmm_gv/software/rsl/quick_ref.php","key":"DUVdzDNrdM"}],"key":"VnYaGCJyYV"},{"type":"heading","depth":2,"position":{"start":{"line":21,"column":1},"end":{"line":21,"column":1}},"children":[{"type":"text","value":"User group or forum page","position":{"start":{"line":21,"column":1},"end":{"line":21,"column":1}},"key":"zIaoSlFinj"}],"identifier":"user-group-or-forum-page","label":"User group or forum page","html_id":"user-group-or-forum-page","implicit":true,"key":"oZnzUym3Sq"},{"type":"paragraph","position":{"start":{"line":22,"column":1},"end":{"line":22,"column":1}},"children":[{"type":"text","value":"N/A","position":{"start":{"line":22,"column":1},"end":{"line":22,"column":1}},"key":"FpTfkK7WE6"}],"key":"HnYfczlYE1"},{"type":"heading","depth":2,"position":{"start":{"line":24,"column":1},"end":{"line":24,"column":1}},"children":[{"type":"text","value":"License model","position":{"start":{"line":24,"column":1},"end":{"line":24,"column":1}},"key":"SGOleJwUdw"}],"identifier":"license-model","label":"License model","html_id":"license-model","implicit":true,"key":"S7F4OGBElD"},{"type":"paragraph","position":{"start":{"line":25,"column":1},"end":{"line":25,"column":1}},"children":[{"type":"text","value":"GNU Lesser General Public License (LGPL)","position":{"start":{"line":25,"column":1},"end":{"line":25,"column":1}},"key":"Ry50vA8B8E"}],"key":"d2EdnRsn3v"},{"type":"heading","depth":2,"position":{"start":{"line":27,"column":1},"end":{"line":27,"column":1}},"children":[{"type":"text","value":"Year of first release","position":{"start":{"line":27,"column":1},"end":{"line":27,"column":1}},"key":"yIiIWcRT3L"}],"identifier":"year-of-first-release","label":"Year of first release","html_id":"year-of-first-release","implicit":true,"key":"sUgPA2sfnD"},{"type":"paragraph","position":{"start":{"line":28,"column":1},"end":{"line":28,"column":1}},"children":[{"type":"text","value":"1999","position":{"start":{"line":28,"column":1},"end":{"line":28,"column":1}},"key":"YfTRNOHrDJ"}],"key":"A3txVFeQ6M"},{"type":"heading","depth":2,"position":{"start":{"line":30,"column":1},"end":{"line":30,"column":1}},"children":[{"type":"text","value":"Main programming laguage(s)","position":{"start":{"line":30,"column":1},"end":{"line":30,"column":1}},"key":"GHq95mZtU7"}],"identifier":"main-programming-laguage-s","label":"Main programming laguage(s)","html_id":"main-programming-laguage-s","implicit":true,"key":"I1cqUZzXvB"},{"type":"paragraph","position":{"start":{"line":31,"column":1},"end":{"line":31,"column":1}},"children":[{"type":"text","value":"C","position":{"start":{"line":31,"column":1},"end":{"line":31,"column":1}},"key":"WFwaxJ4nps"}],"key":"ftFv54IbCS"},{"type":"heading","depth":2,"position":{"start":{"line":33,"column":1},"end":{"line":33,"column":1}},"children":[{"type":"text","value":"Supported platforms","position":{"start":{"line":33,"column":1},"end":{"line":33,"column":1}},"key":"t95K3O2c26"}],"identifier":"supported-platforms","label":"Supported platforms","html_id":"supported-platforms","implicit":true,"key":"zqHAGfHK8f"},{"type":"paragraph","position":{"start":{"line":34,"column":1},"end":{"line":34,"column":1}},"children":[{"type":"text","value":"Linux","position":{"start":{"line":34,"column":1},"end":{"line":34,"column":1}},"key":"wQYFw5ko8P"}],"key":"VNssj01SAd"},{"type":"heading","depth":2,"position":{"start":{"line":36,"column":1},"end":{"line":36,"column":1}},"children":[{"type":"text","value":"Type of software","position":{"start":{"line":36,"column":1},"end":{"line":36,"column":1}},"key":"vMchRcY3bB"}],"identifier":"type-of-software","label":"Type of software","html_id":"type-of-software","implicit":true,"key":"p30gjMSlCX"},{"type":"paragraph","position":{"start":{"line":37,"column":1},"end":{"line":37,"column":1}},"children":[{"type":"text","value":"API/Library","position":{"start":{"line":37,"column":1},"end":{"line":37,"column":1}},"key":"vVOs3hzuOT"}],"key":"Ki6PrfCwzJ"},{"type":"heading","depth":2,"position":{"start":{"line":39,"column":1},"end":{"line":39,"column":1}},"children":[{"type":"text","value":"Further details","position":{"start":{"line":39,"column":1},"end":{"line":39,"column":1}},"key":"TRvlybKAcu"}],"identifier":"further-details","label":"Further details","html_id":"further-details","implicit":true,"key":"L3Z3bVajQu"},{"type":"paragraph","position":{"start":{"line":40,"column":1},"end":{"line":40,"column":1}},"children":[{"type":"text","value":"N/A","position":{"start":{"line":40,"column":1},"end":{"line":40,"column":1}},"key":"aVK9BRff35"}],"key":"DnmwoUcuNB"},{"type":"heading","depth":2,"position":{"start":{"line":42,"column":1},"end":{"line":42,"column":1}},"children":[{"type":"text","value":"References","position":{"start":{"line":42,"column":1},"end":{"line":42,"column":1}},"key":"ucwxqObzsr"}],"identifier":"references","label":"References","html_id":"references","implicit":true,"key":"gWXLt2vba2"},{"type":"paragraph","position":{"start":{"line":43,"column":1},"end":{"line":43,"column":1}},"children":[{"type":"text","value":"N/A","position":{"start":{"line":43,"column":1},"end":{"line":43,"column":1}},"key":"NECgQRU9uF"}],"key":"BFKApHZoXm"}],"key":"mCqyRMQZpB"}],"key":"pv42QP27cz"},"references":{"cite":{"order":[],"data":{}}},"footer":{"navigation":{"prev":{"title":"RSL in IDL","url":"/rsl-in-idl","group":"OpenRadarScience"},"next":{"title":"wradlib","url":"/wradlib","group":"OpenRadarScience"}}},"domain":"http://localhost:3000"}